[{"Phénomène":"Vagues de chaleur","Impact à 1,5°C":"Fortes hausses des températures extrêmes dans la plupart des régions.","Impact à 2°C":"Environ 420 millions de personnes supplémentaires seraient exposées à des vagues de chaleur extrêmes."},{"Phénomène":"Biodiversité","Impact à 1,5°C":"Perte de plus de la moitié de l'aire de répartition pour 6% des insectes, 8% des plantes et 4% des vertébrés.","Impact à 2°C":"Ces chiffres doublent ou triplent : 18% des insectes, 16% des plantes et 8% des vertébrés perdraient leur habitat."},{"Phénomène":"Océans & Coraux","Impact à 1,5°C":"Déclin de 70 à 90% des récifs coralliens tropicaux.","Impact à 2°C":"Disparition quasi totale (>99%) des récifs coralliens."},{"Phénomène":"Niveau de la mer","Impact à 1,5°C":"Hausse projetée de 0,26 à 0,77 m d'ici 2100.","Impact à 2°C":"Hausse supérieure de 0,1 m par rapport au scénario 1,5°C, exposant 10 millions de personnes de plus aux risques côtiers."},{"Phénomène":"Arctique","Impact à 1,5°C":"Un été sans glace de mer environ tous les 100 ans.","Impact à 2°C":"Un été sans glace de mer au moins tous les 10 ans."}]